{
"__comment": "Designed by - with BDcraft Cubik PRO 0.90 Beta - http://bdcraft.net",
"textures": {
    "texture": "items/headstonefront",
    "tombstonebackandside": "items/tombstonebackandside"
},
"elements": [ 
{
    "from": [ 0.5, 0, 7 ],
    "to": [ 15.5, 10.5, 9 ],
    "faces": {
        "down":  { "uv": [ 15.5, 10.5, 0.5, 8.5 ], "texture": "#texture" },
        "up":    { "uv": [ 0.5, 8.5, 15.5, 10.5 ], "texture": "#texture" },
        "north": { "uv": [ 0.5, 5.5, 15.5, 16 ], "texture": "#texture" },
        "south": { "uv": [ 0.5, 5.5, 15.5, 16 ], "texture": "#texture" },
        "west":  { "uv": [ 13.5, 5.5, 15.5, 16 ], "texture": "#texture" },
        "east":  { "uv": [ 0.5, 5.5, 2.5, 16 ], "texture": "#texture" }
    }
},
{
    "from": [ 1, 10.5, 7 ],
    "to": [ 15, 11.5, 9 ],
    "faces": {
        "down":  { "uv": [ 15, 9, 1, 7 ], "texture": "#texture" },
        "up":    { "uv": [ 1, 7, 15, 9 ], "texture": "#texture" },
        "north": { "uv": [ 1, 4.5, 15, 5.5 ], "texture": "#texture" },
        "south": { "uv": [ 1, 4.5, 15, 5.5 ], "texture": "#texture" },
        "west":  { "uv": [ 7, 4.5, 9, 5.5 ], "texture": "#texture" },
        "east":  { "uv": [ 7, 4.5, 9, 5.5 ], "texture": "#texture" }
    }
},
{
    "from": [ 1.5, 11.5, 7 ],
    "to": [ 14.5, 12.5, 9 ],
    "faces": {
        "down":  { "uv": [ 14.5, 9, 1.5, 7 ], "texture": "#texture" },
        "up":    { "uv": [ 1.5, 7, 14.5, 9 ], "texture": "#texture" },
        "north": { "uv": [ 1.5, 3.5, 14.5, 4.5 ], "texture": "#texture" },
        "south": { "uv": [ 1.5, 3.5, 14.5, 4.5 ], "texture": "#texture" },
        "west":  { "uv": [ 7, 3.5, 9, 4.5 ], "texture": "#texture" },
        "east":  { "uv": [ 7, 3.5, 9, 4.5 ], "texture": "#texture" }
    }
},
{
    "from": [ 2, 12.5, 7 ],
    "to": [ 14, 13, 9 ],
    "faces": {
        "down":  { "uv": [ 14, 9, 2, 7 ], "texture": "#texture" },
        "up":    { "uv": [ 2, 7, 14, 9 ], "texture": "#texture" },
        "north": { "uv": [ 2, 3, 14, 3.5 ], "texture": "#texture" },
        "south": { "uv": [ 2, 3, 14, 3.5 ], "texture": "#texture" },
        "west":  { "uv": [ 7, 3, 9, 3.5 ], "texture": "#texture" },
        "east":  { "uv": [ 7, 3, 9, 3.5 ], "texture": "#texture" }
    }
},
{
    "from": [ 2.5, 13, 7 ],
    "to": [ 13.5, 13.5, 9 ],
    "faces": {
        "down":  { "uv": [ 13.5, 9, 2.5, 7 ], "texture": "#texture" },
        "up":    { "uv": [ 2.5, 7, 13.5, 9 ], "texture": "#texture" },
        "north": { "uv": [ 2.5, 2.5, 13.5, 3 ], "texture": "#texture" },
        "south": { "uv": [ 2.5, 2.5, 13.5, 3 ], "texture": "#texture" },
        "west":  { "uv": [ 7, 2.5, 9, 3 ], "texture": "#texture" },
        "east":  { "uv": [ 7, 2.5, 9, 3 ], "texture": "#texture" }
    }
},
{
    "from": [ 3, 13.5, 7 ],
    "to": [ 13, 14, 9 ],
    "faces": {
        "down":  { "uv": [ 13, 9, 3, 7 ], "texture": "#texture" },
        "up":    { "uv": [ 3, 7, 13, 9 ], "texture": "#texture" },
        "north": { "uv": [ 3, 2, 13, 2.5 ], "texture": "#texture" },
        "south": { "uv": [ 3, 2, 13, 2.5 ], "texture": "#texture" },
        "west":  { "uv": [ 7, 2, 9, 2.5 ], "texture": "#texture" },
        "east":  { "uv": [ 7, 2, 9, 2.5 ], "texture": "#texture" }
    }
},
{
    "from": [ 4, 14, 7 ],
    "to": [ 12, 14.5, 9 ],
    "faces": {
        "down":  { "uv": [ 4, 1.5, 12, 3.5 ], "texture": "#texture" },
        "up":    { "uv": [ 4, 1.5, 12, 3.5 ], "texture": "#texture" },
        "north": { "uv": [ 4, 1.5, 12, 2 ], "texture": "#texture" },
        "south": { "uv": [ 4, 1.5, 12, 2 ], "texture": "#texture" },
        "west":  { "uv": [ 7, 1.5, 9, 2 ], "texture": "#texture" },
        "east":  { "uv": [ 7, 1.5, 9, 2 ], "texture": "#texture" }
    }
},
{
    "from": [ 5, 14.5, 7 ],
    "to": [ 11, 15, 9 ],
    "faces": {
        "down":  { "uv": [ 11, 3, 5, 1 ], "texture": "#texture" },
        "up":    { "uv": [ 5, 1, 11, 3 ], "texture": "#texture" },
        "north": { "uv": [ 5, 1, 11, 1.5 ], "texture": "#texture" },
        "south": { "uv": [ 5, 1, 11, 1.5 ], "texture": "#texture" },
        "west":  { "uv": [ 7, 1, 9, 1.5 ], "texture": "#texture" },
        "east":  { "uv": [ 7, 1, 9, 1.5 ], "texture": "#texture" }
    }
},
{
    "from": [ 0.5, -8, 7 ],
    "to": [ 15.5, 0, 9 ],
    "faces": {
        "down":  { "uv": [ 15.5, 13.5, 0.5, 11.5 ], "texture": "#tombstonebackandside" },
        "up":    { "uv": [ 0.5, 9.5, 15.5, 11.5 ], "texture": "#tombstonebackandside" },
        "north": { "uv": [ 0.5, 8.5, 15.5, 16 ], "texture": "#tombstonebackandside" },
        "south": { "uv": [ 0.5, 8.5, 15.5, 16 ], "texture": "#tombstonebackandside" },
        "west":  { "uv": [ 0, 8.5, 2, 16 ], "texture": "#tombstonebackandside" },
        "east":  { "uv": [ 0, 8.5, 2, 16 ], "texture": "#tombstonebackandside" }
    }
}
]
}