{
"__comment": "Designed by Hypixel minecraft server with BDcraft Cubik PRO 0.92 Beta - http://bdcraft.net",
"textures": {
    "texture": "items/Lightning_Nova",
	"particle": "items/Lightning_Nova"
},
"elements": [ 
{
    "from": [ 8, -10, -10 ],
    "to": [ 8.0625, 30, 26 ],
    "faces": {
        "west":  { "uv": [ 0, 0, 16, 16 ], "texture": "#texture" },
        "east":  { "uv": [ 0, 0, 16, 16 ], "texture": "#texture" }
    }
},
{
    "from": [ -10, -10, 8 ],
    "to": [ 26, 30, 8.0625 ],
    "faces": {
        "north": { "uv": [ 0, 0, 16, 16 ], "texture": "#texture" },
        "south": { "uv": [ 0, 0, 16, 16 ], "texture": "#texture" }
    }
}
],
"display": {
    "head": {
        "rotation": [ 0, 0, 0 ],
        "translation": [ 0, -22, 0 ],
        "scale": [ 3.5, 3.5, 3.5 ]
    }
}
}